{
    "layout": "product",
    "type": "men",
    "hidden": false,
    "discount": 32,
    "title": "Elegant Soft Shirt",
    "createdAt": "2009-01-31T16:45:11.068Z",
    "imagePreview": "images/fake-image-6.jpg",
    "images": [
        "images/fake-image-1.jpg",
        "images/fake-image-2.jpg",
        "images/fake-image-3.jpg",
        "images/fake-image-4.jpg",
        "images/fake-image-5.jpg",
        "images/fake-image-6.jpg"
    ],
    "price": 246,
    "category": "boots",
    "body": "The slim & simple Maple Gaming Keyboard from Dev Byte comes with a sleek body and 7- Color RGB LED Back-lighting for smart functionality\n                Ergonomic executive chair upholstered in bonded black leather and PVC padded seat and back for all-day comfort and support\n                A magnam delectus quasi. Voluptatem impedit tenetur. Omnis quis aut neque quod earum. Est deleniti magni. Magni quos facilis. Officia aperiam iste similique.\nQuibusdam doloremque quas in consequatur. Illo nesciunt est quibusdam cumque sunt tempore. Facilis deserunt beatae repellendus magni aperiam sequi. Odit eveniet mollitia debitis. Facere voluptatem voluptatum accusamus veritatis."
}