{
    "layout": "product",
    "type": "men",
    "hidden": false,
    "discount": 9,
    "title": "Sleek Fresh Fish",
    "careatedAt": "2020-09-23T15:25:50.084Z",
    "imagePreview": "../../images/fake-image-3.jpg",
    "images": [
        "../../images/fake-image-1.jpg",
        "../../images/fake-image-2.jpg",
        "../../images/fake-image-3.jpg",
        "../../images/fake-image-4.jpg",
        "../../images/fake-image-5.jpg",
        "../../images/fake-image-6.jpg"
    ],
    "price": 83,
    "category": "Salad",
    "body": "The automobile layout consists of a front-engine design, with transaxle-type transmissions mounted at the rear of the engine and four wheel drive\n                New ABC 13 9370, 13.3, 5th Gen CoreA5-8250U, 8GB RAM, 256GB SSD, power UHD Graphics, OS 10 Home, OS Office A & J 2016\n                Quibusdam dolor assumenda. Sunt explicabo maxime dolorum. Non amet repellat inventore eos reprehenderit cum quasi. Rerum aut dolore labore autem. Maxime laboriosam et dolor.\n \rDolor cupiditate labore rerum dolor odio. Eaque error aliquid. Qui eos ad et labore voluptas in officiis dolorum. Veritatis quas qui. Ab et et magnam neque dolorem ut voluptatum molestias ratione."
}