{
    "layout": "product",
    "type": "boys",
    "hidden": false,
    "discount": 0,
    "title": "Bespoke Wooden Chips",
    "createdAt": "2007-10-08T04:17:08.898Z",
    "imagePreview": "images/fake-image-3.jpg",
    "images": [
        "images/fake-image-1.jpg",
        "images/fake-image-2.jpg",
        "images/fake-image-3.jpg",
        "images/fake-image-4.jpg",
        "images/fake-image-5.jpg",
        "images/fake-image-6.jpg"
    ],
    "price": 774,
    "category": "sweatshirt",
    "body": "The Football Is Good For Training And Recreational Purposes\n                The slim & simple Maple Gaming Keyboard from Dev Byte comes with a sleek body and 7- Color RGB LED Back-lighting for smart functionality\n                Repellendus error excepturi quidem ipsam placeat magni. Enim illo occaecati molestiae illo. Et rerum molestiae dignissimos autem.\nNon esse ullam dicta ducimus eum accusamus odio expedita. Commodi optio voluptatem deleniti commodi mollitia aspernatur at excepturi delectus. Dolorem adipisci veniam."
}