{
    "layout": "product",
    "type": "women",
    "hidden": false,
    "discount": 27,
    "title": "Ergonomic Steel Hat",
    "careatedAt": "2021-06-28T03:09:55.827Z",
    "imagePreview": "../../images/fake-image-2.jpg",
    "images": [
        "../../images/fake-image-1.jpg",
        "../../images/fake-image-2.jpg",
        "../../images/fake-image-3.jpg",
        "../../images/fake-image-4.jpg",
        "../../images/fake-image-5.jpg",
        "../../images/fake-image-6.jpg"
    ],
    "price": 923,
    "category": "Salad",
    "body": "The Nagasaki Lander is the trademarked name of several series of Nagasaki sport bikes, that started with the 1984 ABC800J\n                The Nagasaki Lander is the trademarked name of several series of Nagasaki sport bikes, that started with the 1984 ABC800J\n                Sint nulla maxime suscipit. A tempore labore. Amet facere quis porro. Eum voluptas libero in quia voluptatem sint amet eveniet. Aliquid aut nesciunt et iste ea. Esse ut et velit.\n \rSaepe aut et maiores omnis. Est eum sed illo ut est nisi fugit sed sed. Doloremque nobis qui temporibus accusantium quod sapiente enim facere voluptate."
}