{
    "layout": "product",
    "type": "women",
    "hidden": false,
    "discount": 18,
    "title": "Small Bronze Shoes",
    "createdAt": "2015-08-25T08:32:52.979Z",
    "imagePreview": "images/fake-image-1.jpg",
    "images": [
        "images/fake-image-1.jpg",
        "images/fake-image-2.jpg",
        "images/fake-image-3.jpg",
        "images/fake-image-4.jpg",
        "images/fake-image-5.jpg",
        "images/fake-image-6.jpg"
    ],
    "price": 897,
    "category": "sweatshirt",
    "body": "Andy shoes are designed to keeping in mind durability as well as trends, the most stylish range of shoes & sandals\n                New range of formal shirts are designed keeping you in mind. With fits and styling that will make you stand apart\n                Esse laudantium assumenda atque accusantium consequuntur magnam esse. Vitae eum dolorum quisquam accusamus pariatur. Omnis sed excepturi minima nemo suscipit harum autem.\nLaudantium nobis ipsum. Nihil nesciunt nobis esse exercitationem vero mollitia corporis. Exercitationem quaerat cumque delectus maxime similique architecto sed commodi ex. Eius autem quasi reprehenderit dicta. Accusantium atque enim quis architecto. Adipisci fugiat aspernatur officia voluptate accusamus."
}